{
  "items": [
    {
      "kind": "youtube#searchResult",
      "etag": "JYI5c09hOQgEAeW202s4NjsMHzY",
      "id": {
        "kind": "youtube#video",
        "videoId": "w7M0-AEjnQE"
      },
      "snippet": {
        "publishedAt": "2022-05-12T09:02:21Z",
        "channelId": "UCChjE9CYTSJUECtLkA3SnTw",
        "title": "Mob Psycho 100 Season 3 - Official Trailer | AniTV",
        "description": "Mob Psycho 100, Mob Psycho 100 anime, Mob Psycho 100 trailer, Mob Psycho 100 anime trailer, Mob Psycho 100 release date, ...",
        "thumbnails": {
          "default": {
            "url": "https://i.ytimg.com/vi/w7M0-AEjnQE/default.jpg",
            "width": 120,
            "height": 90
          },
          "medium": {
            "url": "https://i.ytimg.com/vi/w7M0-AEjnQE/mqdefault.jpg",
            "width": 320,
            "height": 180
          },
          "high": {
            "url": "https://i.ytimg.com/vi/w7M0-AEjnQE/hqdefault.jpg",
            "width": 480,
            "height": 360
          }
        },
        "channelTitle": "AniTV",
        "liveBroadcastContent": "none",
        "publishTime": "2022-05-12T09:02:21Z"
      }
    },
    {
      "kind": "youtube#searchResult",
      "etag": "KAHabL6ELJsCwOWZsdjgxct4MNg",
      "id": {
        "kind": "youtube#video",
        "videoId": "t5CIs0jDqC8"
      },
      "snippet": {
        "publishedAt": "2022-05-10T15:00:29Z",
        "channelId": "UC6pGDc4bFGD1_36IKv3FnYg",
        "title": "Dragon Ball Super: SUPER HERO | OFFICIAL TRAILER",
        "description": "Dragon Ball Super: SUPER HERO is coming to theaters Summer 2022! More info here! https://got.cr/cc-dbsshpv Crunchyroll ...",
        "thumbnails": {
          "default": {
            "url": "https://i.ytimg.com/vi/t5CIs0jDqC8/default.jpg",
            "width": 120,
            "height": 90
          },
          "medium": {
            "url": "https://i.ytimg.com/vi/t5CIs0jDqC8/mqdefault.jpg",
            "width": 320,
            "height": 180
          },
          "high": {
            "url": "https://i.ytimg.com/vi/t5CIs0jDqC8/hqdefault.jpg",
            "width": 480,
            "height": 360
          }
        },
        "channelTitle": "Crunchyroll Collection",
        "liveBroadcastContent": "none",
        "publishTime": "2022-05-10T15:00:29Z"
      }
    },
    {
      "kind": "youtube#searchResult",
      "etag": "MDtEkRXsGhp6GIEjLpAD8kmTDxY",
      "id": {
        "kind": "youtube#video",
        "videoId": "r518nf259ZE"
      },
      "snippet": {
        "publishedAt": "2022-04-18T16:03:20Z",
        "channelId": "UCJWDdJyZROXdKY22BkwYNUQ",
        "title": "Blades of the Guardians - Official Trailer",
        "description": "Blades of the Guardians - Official Anime Trailer \"Hyoujin: BLADES OF THE GUARDIANS,\" based on a popular historical martial ...",
        "thumbnails": {
          "default": {
            "url": "https://i.ytimg.com/vi/r518nf259ZE/default.jpg",
            "width": 120,
            "height": 90
          },
          "medium": {
            "url": "https://i.ytimg.com/vi/r518nf259ZE/mqdefault.jpg",
            "width": 320,
            "height": 180
          },
          "high": {
            "url": "https://i.ytimg.com/vi/r518nf259ZE/hqdefault.jpg",
            "width": 480,
            "height": 360
          }
        },
        "channelTitle": "AnimeHypeアニメ日本",
        "liveBroadcastContent": "none",
        "publishTime": "2022-04-18T16:03:20Z"
      }
    },
    {
      "kind": "youtube#searchResult",
      "etag": "aMsjv9kwYayi8dXoESjdRWXxyVw",
      "id": {
        "kind": "youtube#video",
        "videoId": "fQ6PRbh-ntM"
      },
      "snippet": {
        "publishedAt": "2021-01-21T20:44:38Z",
        "channelId": "UCnl0ms44D6N4yagiFjmQveQ",
        "title": "If Anime Itself had a Trailer",
        "description": "Put a long time into making this I hope you guys enjoy :)",
        "thumbnails": {
          "default": {
            "url": "https://i.ytimg.com/vi/fQ6PRbh-ntM/default.jpg",
            "width": 120,
            "height": 90
          },
          "medium": {
            "url": "https://i.ytimg.com/vi/fQ6PRbh-ntM/mqdefault.jpg",
            "width": 320,
            "height": 180
          },
          "high": {
            "url": "https://i.ytimg.com/vi/fQ6PRbh-ntM/hqdefault.jpg",
            "width": 480,
            "height": 360
          }
        },
        "channelTitle": "The Last Starboy",
        "liveBroadcastContent": "none",
        "publishTime": "2021-01-21T20:44:38Z"
      }
    },
    {
      "kind": "youtube#searchResult",
      "etag": "6xaSD5bOPEhRYqP3keK_AOvjNsI",
      "id": {
        "kind": "youtube#video",
        "videoId": "XVlptZSCm3c"
      },
      "snippet": {
        "publishedAt": "2022-05-09T09:02:37Z",
        "channelId": "UCChjE9CYTSJUECtLkA3SnTw",
        "title": "Teasing Master Takagi-san Movie - Official Trailer | AniTV",
        "description": "Teasing Master Takagi-san Movie, Teasing Master Takagi san, Teasing Master Takagi-san Movie trailer, Teasing Master ...",
        "thumbnails": {
          "default": {
            "url": "https://i.ytimg.com/vi/XVlptZSCm3c/default.jpg",
            "width": 120,
            "height": 90
          },
          "medium": {
            "url": "https://i.ytimg.com/vi/XVlptZSCm3c/mqdefault.jpg",
            "width": 320,
            "height": 180
          },
          "high": {
            "url": "https://i.ytimg.com/vi/XVlptZSCm3c/hqdefault.jpg",
            "width": 480,
            "height": 360
          }
        },
        "channelTitle": "AniTV",
        "liveBroadcastContent": "none",
        "publishTime": "2022-05-09T09:02:37Z"
      }
    },
    {
      "kind": "youtube#searchResult",
      "etag": "uvaZvboxFrhpjsv6ISv9Bc6o3U8",
      "id": {
        "kind": "youtube#video",
        "videoId": "eeZ1Ufdra0E"
      },
      "snippet": {
        "publishedAt": "2021-03-22T16:02:37Z",
        "channelId": "UCV63bDvnmGOOp3xRjosVvvA",
        "title": "If Anime In General Had A Trailer 2",
        "description": "Instagram @uniquevfx Tiktok @uniquevfx I had to extend this and add my watermark throughout the entire video, because people ...",
        "thumbnails": {
          "default": {
            "url": "https://i.ytimg.com/vi/eeZ1Ufdra0E/default.jpg",
            "width": 120,
            "height": 90
          },
          "medium": {
            "url": "https://i.ytimg.com/vi/eeZ1Ufdra0E/mqdefault.jpg",
            "width": 320,
            "height": 180
          },
          "high": {
            "url": "https://i.ytimg.com/vi/eeZ1Ufdra0E/hqdefault.jpg",
            "width": 480,
            "height": 360
          }
        },
        "channelTitle": "uniquevfx AMV",
        "liveBroadcastContent": "none",
        "publishTime": "2021-03-22T16:02:37Z"
      }
    },
    {
      "kind": "youtube#searchResult",
      "etag": "-gbyvIZMUEsmdHbE7v3T_oUdZFI",
      "id": {
        "kind": "youtube#video",
        "videoId": "b1miJsAVYJA"
      },
      "snippet": {
        "publishedAt": "2022-05-12T09:00:24Z",
        "channelId": "UCcjqSFXBg2cGQg5r0YooMiA",
        "title": "【ENG sub】アニメ「モブサイコ100 Ⅲ」ティザーPV / MOB PSYCHO 100 III Teaser Trailer",
        "description": "2022年10月 放送開始予定！！！ Streaming begins in October 2022!!! ▽アニメ「モブサイコ100 Ⅲ」あらすじ 何かが「100」に ...",
        "thumbnails": {
          "default": {
            "url": "https://i.ytimg.com/vi/b1miJsAVYJA/default.jpg",
            "width": 120,
            "height": 90
          },
          "medium": {
            "url": "https://i.ytimg.com/vi/b1miJsAVYJA/mqdefault.jpg",
            "width": 320,
            "height": 180
          },
          "high": {
            "url": "https://i.ytimg.com/vi/b1miJsAVYJA/hqdefault.jpg",
            "width": 480,
            "height": 360
          }
        },
        "channelTitle": "Warner Bros. Japan Anime",
        "liveBroadcastContent": "none",
        "publishTime": "2022-05-12T09:00:24Z"
      }
    },
    {
      "kind": "youtube#searchResult",
      "etag": "iFe1AQCJi69IiDKoKfrCt5OqJO8",
      "id": {
        "kind": "youtube#video",
        "videoId": "47gbgcYyxdg"
      },
      "snippet": {
        "publishedAt": "2022-05-11T13:04:25Z",
        "channelId": "UCChjE9CYTSJUECtLkA3SnTw",
        "title": "Ao Ashi - Official Trailer 3 | AniTV",
        "description": "Ao ashi, Ao ashi anime, Ao ashi trailer, Ao ashi anime trailer, Ao ashi trailer eng sub, Ao ashi anime trailer eng sub, Ao ashi ...",
        "thumbnails": {
          "default": {
            "url": "https://i.ytimg.com/vi/47gbgcYyxdg/default.jpg",
            "width": 120,
            "height": 90
          },
          "medium": {
            "url": "https://i.ytimg.com/vi/47gbgcYyxdg/mqdefault.jpg",
            "width": 320,
            "height": 180
          },
          "high": {
            "url": "https://i.ytimg.com/vi/47gbgcYyxdg/hqdefault.jpg",
            "width": 480,
            "height": 360
          }
        },
        "channelTitle": "AniTV",
        "liveBroadcastContent": "none",
        "publishTime": "2022-05-11T13:04:25Z"
      }
    },
    {
      "kind": "youtube#searchResult",
      "etag": "mKCpTnAG8FXGtug2Vy6LA-qsWTA",
      "id": {
        "kind": "youtube#video",
        "videoId": "eyonP1AgC0k"
      },
      "snippet": {
        "publishedAt": "2021-06-27T11:01:02Z",
        "channelId": "UCJWDdJyZROXdKY22BkwYNUQ",
        "title": "Chainsaw Man - Official Trailer",
        "description": "Chainsaw Man - Official Trailer Chainsaw Man is a Japanese manga series written and illustrated by Tatsuki Fujimoto.",
        "thumbnails": {
          "default": {
            "url": "https://i.ytimg.com/vi/eyonP1AgC0k/default.jpg",
            "width": 120,
            "height": 90
          },
          "medium": {
            "url": "https://i.ytimg.com/vi/eyonP1AgC0k/mqdefault.jpg",
            "width": 320,
            "height": 180
          },
          "high": {
            "url": "https://i.ytimg.com/vi/eyonP1AgC0k/hqdefault.jpg",
            "width": 480,
            "height": 360
          }
        },
        "channelTitle": "AnimeHypeアニメ日本",
        "liveBroadcastContent": "none",
        "publishTime": "2021-06-27T11:01:02Z"
      }
    },
    {
      "kind": "youtube#searchResult",
      "etag": "0H4_b29zpoL4wFg2O9dco5iGowA",
      "id": {
        "kind": "youtube#playlist",
        "playlistId": "PL3opwKhWuRpGyNIMzcCzgFfzA-8kQ2sD9"
      },
      "snippet": {
        "publishedAt": "2020-09-07T23:34:37Z",
        "channelId": "UCDYDdPJKBUfKXcZBw9qwMdw",
        "title": "UPCOMING ANIME 2022 - 2023",
        "description": "Compilation of upcoming anime 2022 - 2023.",
        "thumbnails": {
          "default": {
            "url": "https://i.ytimg.com/vi/99OCqiIcqkM/default.jpg",
            "width": 120,
            "height": 90
          },
          "medium": {
            "url": "https://i.ytimg.com/vi/99OCqiIcqkM/mqdefault.jpg",
            "width": 320,
            "height": 180
          },
          "high": {
            "url": "https://i.ytimg.com/vi/99OCqiIcqkM/hqdefault.jpg",
            "width": 480,
            "height": 360
          }
        },
        "channelTitle": "JP Anime",
        "liveBroadcastContent": "none",
        "publishTime": "2020-09-07T23:34:37Z"
      }
    },
    {
      "kind": "youtube#searchResult",
      "etag": "kE3iYsprSdDC7glOwvmPnoKyif0",
      "id": {
        "kind": "youtube#video",
        "videoId": "gaQCFemx5cQ"
      },
      "snippet": {
        "publishedAt": "2021-10-11T12:30:19Z",
        "channelId": "UCDYDdPJKBUfKXcZBw9qwMdw",
        "title": "Alice and Therese&#39;s Illusion Factory - Official Trailer | English Sub",
        "description": "\"Alice to Therese no Maboroshi Koujou\" is MAPPA's first original anime film. Without any dialogue, the trailer with stunning visuals ...",
        "thumbnails": {
          "default": {
            "url": "https://i.ytimg.com/vi/gaQCFemx5cQ/default.jpg",
            "width": 120,
            "height": 90
          },
          "medium": {
            "url": "https://i.ytimg.com/vi/gaQCFemx5cQ/mqdefault.jpg",
            "width": 320,
            "height": 180
          },
          "high": {
            "url": "https://i.ytimg.com/vi/gaQCFemx5cQ/hqdefault.jpg",
            "width": 480,
            "height": 360
          }
        },
        "channelTitle": "JP Anime",
        "liveBroadcastContent": "none",
        "publishTime": "2021-10-11T12:30:19Z"
      }
    },
    {
      "kind": "youtube#searchResult",
      "etag": "PWPE-OFw6BHPYqJt1q2Y9OKS9z8",
      "id": {
        "kind": "youtube#video",
        "videoId": "eGSL-l95VXw"
      },
      "snippet": {
        "publishedAt": "2021-12-19T03:20:19Z",
        "channelId": "UCJWDdJyZROXdKY22BkwYNUQ",
        "title": "Jujutsu Kaisen 0 Movie - Official Trailer 2",
        "description": "\"Jujutsu Kaisen 0\" scheduled for Winter 2022! GENRES:- Action, Demons, Supernatural, Shounen STAFF:- Original Story: ...",
        "thumbnails": {
          "default": {
            "url": "https://i.ytimg.com/vi/eGSL-l95VXw/default.jpg",
            "width": 120,
            "height": 90
          },
          "medium": {
            "url": "https://i.ytimg.com/vi/eGSL-l95VXw/mqdefault.jpg",
            "width": 320,
            "height": 180
          },
          "high": {
            "url": "https://i.ytimg.com/vi/eGSL-l95VXw/hqdefault.jpg",
            "width": 480,
            "height": 360
          }
        },
        "channelTitle": "AnimeHypeアニメ日本",
        "liveBroadcastContent": "none",
        "publishTime": "2021-12-19T03:20:19Z"
      }
    },
    {
      "kind": "youtube#searchResult",
      "etag": "w_TSJeWL8DmhW1qxXyy0SBbat6w",
      "id": {
        "kind": "youtube#video",
        "videoId": "ofXigq9aIpo"
      },
      "snippet": {
        "publishedAt": "2022-03-18T03:00:17Z",
        "channelId": "UC6pGDc4bFGD1_36IKv3FnYg",
        "title": "SPY x FAMILY | MAIN TRAILER",
        "description": "Watch SPY x FAMILY on Crunchyroll! https://got.cr/cc-sxfpv Crunchyroll Collection brings you the latest clips, OPs, and more from ...",
        "thumbnails": {
          "default": {
            "url": "https://i.ytimg.com/vi/ofXigq9aIpo/default.jpg",
            "width": 120,
            "height": 90
          },
          "medium": {
            "url": "https://i.ytimg.com/vi/ofXigq9aIpo/mqdefault.jpg",
            "width": 320,
            "height": 180
          },
          "high": {
            "url": "https://i.ytimg.com/vi/ofXigq9aIpo/hqdefault.jpg",
            "width": 480,
            "height": 360
          }
        },
        "channelTitle": "Crunchyroll Collection",
        "liveBroadcastContent": "none",
        "publishTime": "2022-03-18T03:00:17Z"
      }
    },
    {
      "kind": "youtube#searchResult",
      "etag": "pikk1_TNJ4EFXS1jrTU4nMObV4k",
      "id": {
        "kind": "youtube#video",
        "videoId": "2PAOSbOW2Gg"
      },
      "snippet": {
        "publishedAt": "2021-08-12T09:13:33Z",
        "channelId": "UCJWDdJyZROXdKY22BkwYNUQ",
        "title": "Blue Lock - Official Trailer (HD)",
        "description": "Blue Lock - Official Trailer (HD) TV ANIME \"BLUE LOCK\" is slated for a 2022 release! Synopsis After reflecting on the current state ...",
        "thumbnails": {
          "default": {
            "url": "https://i.ytimg.com/vi/2PAOSbOW2Gg/default.jpg",
            "width": 120,
            "height": 90
          },
          "medium": {
            "url": "https://i.ytimg.com/vi/2PAOSbOW2Gg/mqdefault.jpg",
            "width": 320,
            "height": 180
          },
          "high": {
            "url": "https://i.ytimg.com/vi/2PAOSbOW2Gg/hqdefault.jpg",
            "width": 480,
            "height": 360
          }
        },
        "channelTitle": "AnimeHypeアニメ日本",
        "liveBroadcastContent": "none",
        "publishTime": "2021-08-12T09:13:33Z"
      }
    },
    {
      "kind": "youtube#searchResult",
      "etag": "R8szqk26wizdobg9LR9kkcBWrNM",
      "id": {
        "kind": "youtube#video",
        "videoId": "8pbWblLkHHk"
      },
      "snippet": {
        "publishedAt": "2022-02-28T22:00:01Z",
        "channelId": "UCWOA1ZGywLbqmigxE4Qlvuw",
        "title": "Bubble | Official Trailer | Netflix",
        "description": "In a Tokyo where gravity has broken, a boy and a girl are drawn to each other... The story is set in Tokyo, after bubbles that broke ...",
        "thumbnails": {
          "default": {
            "url": "https://i.ytimg.com/vi/8pbWblLkHHk/default.jpg",
            "width": 120,
            "height": 90
          },
          "medium": {
            "url": "https://i.ytimg.com/vi/8pbWblLkHHk/mqdefault.jpg",
            "width": 320,
            "height": 180
          },
          "high": {
            "url": "https://i.ytimg.com/vi/8pbWblLkHHk/hqdefault.jpg",
            "width": 480,
            "height": 360
          }
        },
        "channelTitle": "Netflix",
        "liveBroadcastContent": "none",
        "publishTime": "2022-02-28T22:00:01Z"
      }
    },
    {
      "kind": "youtube#searchResult",
      "etag": "s8GBSPfkhy6ig0lRwao1Hgy4ni0",
      "id": {
        "kind": "youtube#video",
        "videoId": "UyDlSmU7uuE"
      },
      "snippet": {
        "publishedAt": "2021-12-19T02:24:13Z",
        "channelId": "UCGPJ-ypIEy4Q9VygoNLl7HQ",
        "title": "Hell&#39;s Paradise: Jigokuraku | Official Trailer",
        "description": "\"Hell's Paradise: Jigokuraku\" TV anime STAFF: Original Story: Yuji Kaku \"Hell's Paradise\" Kusu) Director: Kaori Makita Series ...",
        "thumbnails": {
          "default": {
            "url": "https://i.ytimg.com/vi/UyDlSmU7uuE/default.jpg",
            "width": 120,
            "height": 90
          },
          "medium": {
            "url": "https://i.ytimg.com/vi/UyDlSmU7uuE/mqdefault.jpg",
            "width": 320,
            "height": 180
          },
          "high": {
            "url": "https://i.ytimg.com/vi/UyDlSmU7uuE/hqdefault.jpg",
            "width": 480,
            "height": 360
          }
        },
        "channelTitle": "AnimeTV チェーン",
        "liveBroadcastContent": "none",
        "publishTime": "2021-12-19T02:24:13Z"
      }
    },
    {
      "kind": "youtube#searchResult",
      "etag": "s6TfVM-oKNOolgz5yDlDcnrWZrg",
      "id": {
        "kind": "youtube#video",
        "videoId": "iutQJzAXiWo"
      },
      "snippet": {
        "publishedAt": "2021-12-18T10:20:45Z",
        "channelId": "UCDYDdPJKBUfKXcZBw9qwMdw",
        "title": "BLEACH: Thousand Year Blood War – Official Trailer",
        "description": "\"Bleach: Thousand Year Blood War Arc\" / \"Bleach: Sennen Kessen-hen\" is the continuation of the anime \"Bleach (2004)\", follows ...",
        "thumbnails": {
          "default": {
            "url": "https://i.ytimg.com/vi/iutQJzAXiWo/default.jpg",
            "width": 120,
            "height": 90
          },
          "medium": {
            "url": "https://i.ytimg.com/vi/iutQJzAXiWo/mqdefault.jpg",
            "width": 320,
            "height": 180
          },
          "high": {
            "url": "https://i.ytimg.com/vi/iutQJzAXiWo/hqdefault.jpg",
            "width": 480,
            "height": 360
          }
        },
        "channelTitle": "JP Anime",
        "liveBroadcastContent": "none",
        "publishTime": "2021-12-18T10:20:45Z"
      }
    },
    {
      "kind": "youtube#searchResult",
      "etag": "cQQNCX6oGky0UKp-RUzcWGCd_rc",
      "id": {
        "kind": "youtube#video",
        "videoId": "TcO5kFvz3Ic"
      },
      "snippet": {
        "publishedAt": "2022-04-20T17:39:16Z",
        "channelId": "UCGPJ-ypIEy4Q9VygoNLl7HQ",
        "title": "Chainsaw Man | Official Trailer",
        "description": "Anime adaptation of Tatsuki Fujimoto's Chainsaw Man. The anime is scheduled later this year! STORY Denji's a poor young man ...",
        "thumbnails": {
          "default": {
            "url": "https://i.ytimg.com/vi/TcO5kFvz3Ic/default.jpg",
            "width": 120,
            "height": 90
          },
          "medium": {
            "url": "https://i.ytimg.com/vi/TcO5kFvz3Ic/mqdefault.jpg",
            "width": 320,
            "height": 180
          },
          "high": {
            "url": "https://i.ytimg.com/vi/TcO5kFvz3Ic/hqdefault.jpg",
            "width": 480,
            "height": 360
          }
        },
        "channelTitle": "AnimeTV チェーン",
        "liveBroadcastContent": "none",
        "publishTime": "2022-04-20T17:39:16Z"
      }
    },
    {
      "kind": "youtube#searchResult",
      "etag": "J0717yuILqsoY2fGfCvskrZ_NzQ",
      "id": {
        "kind": "youtube#video",
        "videoId": "6f7BZjnjSM4"
      },
      "snippet": {
        "publishedAt": "2021-12-18T10:41:35Z",
        "channelId": "UCJWDdJyZROXdKY22BkwYNUQ",
        "title": "Chainsaw Man Part 2 - Official Trailer",
        "description": "Chainsaw Man Part 2 - Official Trailer Chainsaw Man is a Japanese manga series written and illustrated by Tatsuki Fujimoto.",
        "thumbnails": {
          "default": {
            "url": "https://i.ytimg.com/vi/6f7BZjnjSM4/default.jpg",
            "width": 120,
            "height": 90
          },
          "medium": {
            "url": "https://i.ytimg.com/vi/6f7BZjnjSM4/mqdefault.jpg",
            "width": 320,
            "height": 180
          },
          "high": {
            "url": "https://i.ytimg.com/vi/6f7BZjnjSM4/hqdefault.jpg",
            "width": 480,
            "height": 360
          }
        },
        "channelTitle": "AnimeHypeアニメ日本",
        "liveBroadcastContent": "none",
        "publishTime": "2021-12-18T10:41:35Z"
      }
    },
    {
      "kind": "youtube#searchResult",
      "etag": "RpPqSJ5wxc5masAOWQk7FB3ld-M",
      "id": {
        "kind": "youtube#video",
        "videoId": "1_vTlsf3qkE"
      },
      "snippet": {
        "publishedAt": "2021-12-05T16:00:00Z",
        "channelId": "UCaWd5_7JhbQBe4dknZhsHJg",
        "title": "Top 10 Anime Trailers That Broke The Internet",
        "description": "These teasers sent fans into a tailspin! Join Ashley as we look over the trailers for anime films and series that set the intenert ...",
        "thumbnails": {
          "default": {
            "url": "https://i.ytimg.com/vi/1_vTlsf3qkE/default.jpg",
            "width": 120,
            "height": 90
          },
          "medium": {
            "url": "https://i.ytimg.com/vi/1_vTlsf3qkE/mqdefault.jpg",
            "width": 320,
            "height": 180
          },
          "high": {
            "url": "https://i.ytimg.com/vi/1_vTlsf3qkE/hqdefault.jpg",
            "width": 480,
            "height": 360
          }
        },
        "channelTitle": "WatchMojo.com",
        "liveBroadcastContent": "none",
        "publishTime": "2021-12-05T16:00:00Z"
      }
    },
    {
      "kind": "youtube#searchResult",
      "etag": "U-qBn8DceNtW6LaGXGNEJy0h2RI",
      "id": {
        "kind": "youtube#video",
        "videoId": "Oqd2C3oZkBU"
      },
      "snippet": {
        "publishedAt": "2021-12-18T01:00:12Z",
        "channelId": "UC6pGDc4bFGD1_36IKv3FnYg",
        "title": "SPY x FAMILY | OFFICIAL TRAILER 2",
        "description": "Watch SPY x FAMILY on Crunchyroll! https://got.cr/cc-sxfpv Crunchyroll Collection brings you the latest clips, OPs, and more from ...",
        "thumbnails": {
          "default": {
            "url": "https://i.ytimg.com/vi/Oqd2C3oZkBU/default.jpg",
            "width": 120,
            "height": 90
          },
          "medium": {
            "url": "https://i.ytimg.com/vi/Oqd2C3oZkBU/mqdefault.jpg",
            "width": 320,
            "height": 180
          },
          "high": {
            "url": "https://i.ytimg.com/vi/Oqd2C3oZkBU/hqdefault.jpg",
            "width": 480,
            "height": 360
          }
        },
        "channelTitle": "Crunchyroll Collection",
        "liveBroadcastContent": "none",
        "publishTime": "2021-12-18T01:00:12Z"
      }
    },
    {
      "kind": "youtube#searchResult",
      "etag": "jN0KmJ0D1Ogz4ISgmZTTktB4NB0",
      "id": {
        "kind": "youtube#video",
        "videoId": "1uWt5uXWUws"
      },
      "snippet": {
        "publishedAt": "2022-02-05T04:04:02Z",
        "channelId": "UCChjE9CYTSJUECtLkA3SnTw",
        "title": "Shikimori&#39;s Not Just a Cutie - Official Trailer [English Sub] | AniTV",
        "description": "Shikimori's Not Just a Cutie anime, Shikimori's Not Just a Cutie anime trailer, Shikimori's Not Just a Cutie anime pv, Shikimori's ...",
        "thumbnails": {
          "default": {
            "url": "https://i.ytimg.com/vi/1uWt5uXWUws/default.jpg",
            "width": 120,
            "height": 90
          },
          "medium": {
            "url": "https://i.ytimg.com/vi/1uWt5uXWUws/mqdefault.jpg",
            "width": 320,
            "height": 180
          },
          "high": {
            "url": "https://i.ytimg.com/vi/1uWt5uXWUws/hqdefault.jpg",
            "width": 480,
            "height": 360
          }
        },
        "channelTitle": "AniTV",
        "liveBroadcastContent": "none",
        "publishTime": "2022-02-05T04:04:02Z"
      }
    },
    {
      "kind": "youtube#searchResult",
      "etag": "qRWLjVQrZixjSKKSH9PRXp84Q1U",
      "id": {
        "kind": "youtube#video",
        "videoId": "rORG4gUVOY8"
      },
      "snippet": {
        "publishedAt": "2022-03-28T09:03:10Z",
        "channelId": "UCChjE9CYTSJUECtLkA3SnTw",
        "title": "Summer Time Render - Official Trailer 2 | AniTV",
        "description": "Summer Time Render, Summer Time Render Anime, Summer Time Anime, Summer Time Render Trailer, Summer Time Render ...",
        "thumbnails": {
          "default": {
            "url": "https://i.ytimg.com/vi/rORG4gUVOY8/default.jpg",
            "width": 120,
            "height": 90
          },
          "medium": {
            "url": "https://i.ytimg.com/vi/rORG4gUVOY8/mqdefault.jpg",
            "width": 320,
            "height": 180
          },
          "high": {
            "url": "https://i.ytimg.com/vi/rORG4gUVOY8/hqdefault.jpg",
            "width": 480,
            "height": 360
          }
        },
        "channelTitle": "AniTV",
        "liveBroadcastContent": "none",
        "publishTime": "2022-03-28T09:03:10Z"
      }
    },
    {
      "kind": "youtube#searchResult",
      "etag": "RryqpbJ-IStNsX-fE7dyk1idg1E",
      "id": {
        "kind": "youtube#video",
        "videoId": "vevYlHV9raY"
      },
      "snippet": {
        "publishedAt": "2021-10-27T12:05:28Z",
        "channelId": "UCDYDdPJKBUfKXcZBw9qwMdw",
        "title": "The Eminence in Shadow - Official Trailer (2022)",
        "description": "\"The Eminence in Shadow,\" an anime adaptation based on the popular light novel \"Kage no Jitsuryokusha ni Naritakute!",
        "thumbnails": {
          "default": {
            "url": "https://i.ytimg.com/vi/vevYlHV9raY/default.jpg",
            "width": 120,
            "height": 90
          },
          "medium": {
            "url": "https://i.ytimg.com/vi/vevYlHV9raY/mqdefault.jpg",
            "width": 320,
            "height": 180
          },
          "high": {
            "url": "https://i.ytimg.com/vi/vevYlHV9raY/hqdefault.jpg",
            "width": 480,
            "height": 360
          }
        },
        "channelTitle": "JP Anime",
        "liveBroadcastContent": "none",
        "publishTime": "2021-10-27T12:05:28Z"
      }
    },
    {
      "kind": "youtube#searchResult",
      "etag": "fat9z5SUkTDUHF2JkAzRqW04_l4",
      "id": {
        "kind": "youtube#video",
        "videoId": "ypPBfhYNOgc"
      },
      "snippet": {
        "publishedAt": "2022-04-30T12:06:42Z",
        "channelId": "UCJWDdJyZROXdKY22BkwYNUQ",
        "title": "Tokyo Revengers Season 2 - Official Announcement Teaser Trailer",
        "description": "Tokyo Revengers Season 2 - Official Announcement Teaser Trailer Tokyo Revengers is a Japanese manga series written and ...",
        "thumbnails": {
          "default": {
            "url": "https://i.ytimg.com/vi/ypPBfhYNOgc/default.jpg",
            "width": 120,
            "height": 90
          },
          "medium": {
            "url": "https://i.ytimg.com/vi/ypPBfhYNOgc/mqdefault.jpg",
            "width": 320,
            "height": 180
          },
          "high": {
            "url": "https://i.ytimg.com/vi/ypPBfhYNOgc/hqdefault.jpg",
            "width": 480,
            "height": 360
          }
        },
        "channelTitle": "AnimeHypeアニメ日本",
        "liveBroadcastContent": "none",
        "publishTime": "2022-04-30T12:06:42Z"
      }
    }
  ]
}
